drag_resize/DragResize.py
drag_resize/__init__.py
drag_resize/_imports_.py
drag_resize/drag_resize.min.js
drag_resize/drag_resize.min.js.map
drag_resize/metadata.json
drag_resize/package-info.json
drag_resize-0.0.4.dist-info/LICENSE
drag_resize-0.0.4.dist-info/METADATA
drag_resize-0.0.4.dist-info/WHEEL
drag_resize-0.0.4.dist-info/top_level.txt
drag_resize-0.0.4.dist-info/RECORD
