Metadata-Version: 2.1
Name: drag-resize
Version: 0.0.4
Summary: drag and resize
Author: Jin Ch <jin236248@gmail.com>
License: MIT
Classifier: Framework :: Dash
License-File: LICENSE
